ckanext_geodatagov-0.4.2-nspkg.pth
ckanext/geodatagov/auth.py
ckanext/geodatagov/cli.py
ckanext/geodatagov/commands.py
ckanext/geodatagov/helpers.py
ckanext/geodatagov/logic.py
ckanext/geodatagov/plugin.py
ckanext/geodatagov/search.py
ckanext/geodatagov/saml2/__init__.py
ckanext/geodatagov/saml2/pkitestcrt/mycert.pem
ckanext/geodatagov/saml2/pkitestcrt/mykey.pem
ckanext/geodatagov/templates/organization/read.html
ckanext/geodatagov/templates/organization/snippets/organization_form.html
ckanext/geodatagov/templates/package/read.html
ckanext/geodatagov/templates/package/search.html
ckanext/geodatagov/templates/snippets/related_collection.html
ckanext/geodatagov/tests/data-samples/waf-collection1/index.html
ckanext/geodatagov/tests/data-samples/waf-collection2/index.html
ckanext/geodatagov/tests/data-samples/waf-fgdc/index.html
ckanext/geodatagov/tests/data-samples/waf-gmi/index.html
ckanext/geodatagov/tests/data-samples/waf-trim-tags/index.html
ckanext/geodatagov/tests/data-samples/waf1/index.html
ckanext/geodatagov/validation/__init__.py
ckanext/geodatagov/validation/xml/fgdc-std-001.1-1999/fgdc-std-001-1998-sect03.xsd
ckanext/geodatagov/validation/xml/fgdc-std-001.1-1999/fgdc-std-001-1998-sect04.xsd
ckanext/geodatagov/validation/xml/fgdc-std-001.1-1999/fgdc-std-001-1998-sect05.xsd
ckanext/geodatagov/validation/xml/fgdc-std-001.1-1999/fgdc-std-001-1998-sect10.xsd
ckanext/geodatagov/validation/xml/fgdc-std-001.1-1999/fgdc-std-001.1-1999-sect01.xsd
ckanext/geodatagov/validation/xml/fgdc-std-001.1-1999/fgdc-std-001.1-1999-sect02.xsd
ckanext/geodatagov/validation/xml/fgdc-std-001.1-1999/fgdc-std-001.1-1999-sect06.xsd
ckanext/geodatagov/validation/xml/fgdc-std-001.1-1999/fgdc-std-001.1-1999-sect07.xsd
ckanext/geodatagov/validation/xml/fgdc-std-001.1-1999/fgdc-std-001.1-1999-sect08.xsd
ckanext/geodatagov/validation/xml/fgdc-std-001.1-1999/fgdc-std-001.1-1999-sect09.xsd
ckanext/geodatagov/validation/xml/fgdc-std-001.1-1999/fgdc-std-001.1-1999.xsd
ckanext_geodatagov-0.4.2.dist-info/LICENSE.md
ckanext_geodatagov-0.4.2.dist-info/METADATA
ckanext_geodatagov-0.4.2.dist-info/WHEEL
ckanext_geodatagov-0.4.2.dist-info/entry_points.txt
ckanext_geodatagov-0.4.2.dist-info/namespace_packages.txt
ckanext_geodatagov-0.4.2.dist-info/top_level.txt
ckanext_geodatagov-0.4.2.dist-info/RECORD
