Metadata-Version: 2.1
Name: ckanext-geodatagov
Version: 0.4.2
Home-page: https://github.com/GSA/ckanext-geodatagov
Author: Data.gov
Author-email: datagovhelp@gsa.gov
Classifier: Programming Language :: Python :: 3
License-File: LICENSE.md
Requires-Dist: boto3
Requires-Dist: ckanext-datajson >=0.1.19
Requires-Dist: ply >=3.4
